image_scraper/__init__.py
image_scraper/__main__.py
image_scraper/config.py
image_scraper/scraper.py
img_scrapr-0.1.1.dist-info/METADATA
img_scrapr-0.1.1.dist-info/WHEEL
img_scrapr-0.1.1.dist-info/entry_points.txt
img_scrapr-0.1.1.dist-info/licenses/LICENSE
img_scrapr-0.1.1.dist-info/RECORD
