Metadata-Version: 2.4
Name: img-scrapr
Version: 0.1.1
Summary: Python package to download images from Google images
Project-URL: Repository, https://github.com/Krishk1223/image_scraper
Project-URL: Issues, https://github.com/Krishk1223/image_scraper/issues
Author-email: Krish Kapoor <krishk122703@gmail.com>
License-Expression: MIT
License-File: LICENSE
Keywords: image,scraper,selenium,web-scraper
Classifier: Development Status :: 3 - Alpha
Classifier: Intended Audience :: Developers
Classifier: Programming Language :: Python :: 3
Classifier: Programming Language :: Python :: 3.11
Classifier: Programming Language :: Python :: 3.12
Classifier: Topic :: Software Development :: Libraries :: Python Modules
Requires-Python: >=3.11
Requires-Dist: pillow>=11.0.0
Requires-Dist: requests>=2.32.3
Requires-Dist: selenium>=4.26.0
Requires-Dist: undetected-chromedriver>=3.5.5
Provides-Extra: dev
Requires-Dist: black>=22.0.0; extra == 'dev'
Requires-Dist: pytest>=7.0.0; extra == 'dev'
Requires-Dist: ruff>=0.1.0; extra == 'dev'
